gambatools/CFGLexer.py
gambatools/CFGParser.py
gambatools/CFGVisitor.py
gambatools/__init__.py
gambatools/algorithms.py
gambatools/automata_checker.py
gambatools/automaton.py
gambatools/automaton_algorithms.py
gambatools/automaton_io.py
gambatools/cfg.py
gambatools/cfg_algorithms.py
gambatools/cfg_parser.py
gambatools/dfa.py
gambatools/dfa_algorithms.py
gambatools/dfa_io.py
gambatools/draw_sigma.py
gambatools/global_settings.py
gambatools/gnfa.py
gambatools/identifier_generator.py
gambatools/language_algorithms.py
gambatools/language_generator.py
gambatools/list_utility.py
gambatools/logging.py
gambatools/nfa.py
gambatools/nfa_algorithms.py
gambatools/nfa_io.py
gambatools/notebook.py
gambatools/notebook_cfg.py
gambatools/notebook_chomsky.py
gambatools/notebook_dfa.py
gambatools/notebook_experimental.py
gambatools/notebook_nfa2dfa.py
gambatools/notebook_sigma.py
gambatools/pda.py
gambatools/pda_algorithms.py
gambatools/printing.py
gambatools/regexp.py
gambatools/regexpLexer.py
gambatools/regexpParser.py
gambatools/regexpVisitor.py
gambatools/regexp_algorithms.py
gambatools/regexp_parser.py
gambatools/regexp_simpleLexer.py
gambatools/regexp_simpleParser.py
gambatools/regexp_simpleVisitor.py
gambatools/regexp_simple_parser.py
gambatools/regular_expressionsLexer.py
gambatools/text_utility.py
gambatools/tm.py
gambatools/tm_algorithms.py
gambatools-0.20.dist-info/LICENSE
gambatools-0.20.dist-info/METADATA
gambatools-0.20.dist-info/WHEEL
gambatools-0.20.dist-info/top_level.txt
gambatools-0.20.dist-info/RECORD
