Metadata-Version: 2.1
Name: gambatools
Version: 0.20
Summary: A library for formal language education. It contains support for DFAs, NFAs, PDAs, Turing machines, context free grammars and regular expressions.
Home-page: https://github.com/wiegerw/gambatools
Author: Wieger Wesselink
Author-email: j.w.wesselink@tue.nl
Project-URL: Bug Tracker, https://github.com/wiegerw/gambatools/issues
Classifier: Programming Language :: Python :: 3
Classifier: License :: OSI Approved :: GNU General Public License v3 or later (GPLv3+)
Classifier: Operating System :: OS Independent
Requires-Python: >=3.6
License-File: LICENSE
